LICENSE.txt
MANIFEST.in
README.md
pyproject.toml
requirements.txt
setup.cfg
setup.py
bnpy/HModel.py
bnpy/Run.py
bnpy/Runner.py
bnpy/__init__.py
bnpy.egg-info/PKG-INFO
bnpy.egg-info/SOURCES.txt
bnpy.egg-info/dependency_links.txt
bnpy.egg-info/not-zip-safe
bnpy.egg-info/requires.txt
bnpy.egg-info/top_level.txt
bnpy/allocmodel/AllocModel.py
bnpy/allocmodel/__init__.py
bnpy/allocmodel/hmm/FiniteHMM.py
bnpy/allocmodel/hmm/HDPHMM.py
bnpy/allocmodel/hmm/HDPHMMUtil.py
bnpy/allocmodel/hmm/HMMUtil.py
bnpy/allocmodel/hmm/__init__.py
bnpy/allocmodel/hmm/lib/FwdBwdRowMajor.cpp
bnpy/allocmodel/hmm/lib/LibFwdBwd.py
bnpy/allocmodel/hmm/lib/__init__.py
bnpy/allocmodel/mix/DPMixtureModel.py
bnpy/allocmodel/mix/DPMixtureRestrictedLocalStep.py
bnpy/allocmodel/mix/FiniteMixtureModel.py
bnpy/allocmodel/mix/__init__.py
bnpy/allocmodel/relational/FiniteAssortativeMMSB.py
bnpy/allocmodel/relational/FiniteMMSB.py
bnpy/allocmodel/relational/FiniteSMSB.py
bnpy/allocmodel/relational/HDPAssortativeMMSB.py
bnpy/allocmodel/relational/HDPMMSB.py
bnpy/allocmodel/relational/__init__.py
bnpy/allocmodel/topics/BetterLocalStep.py
bnpy/allocmodel/topics/FiniteTopicModel.py
bnpy/allocmodel/topics/HDPTopicModel.py
bnpy/allocmodel/topics/HDPTopicRestrictedLocalStep.py
bnpy/allocmodel/topics/HDPTopicRestrictedLocalStep2.py
bnpy/allocmodel/topics/HDPTopicUtil.py
bnpy/allocmodel/topics/LocalStepLogger.py
bnpy/allocmodel/topics/LocalStepManyDocs.py
bnpy/allocmodel/topics/LocalStepSingleDoc.py
bnpy/allocmodel/topics/LocalStepSingleDocSimpler.py
bnpy/allocmodel/topics/OptimizerRhoOmega.py
bnpy/allocmodel/topics/OptimizerRhoOmegaBetter.py
bnpy/allocmodel/topics/__init__.py
bnpy/allocmodel/tree/__init__.py
bnpy/birthmove/BCleanup.py
bnpy/birthmove/BCreateManyProposals.py
bnpy/birthmove/BCreateOneProposal.py
bnpy/birthmove/BLogger.py
bnpy/birthmove/BPlanner.py
bnpy/birthmove/BRestrictedLocalStep.py
bnpy/birthmove/BirthProposalError.py
bnpy/birthmove/TryBirth.py
bnpy/birthmove/__init__.py
bnpy/callbacks/CBCalcHeldoutMetricsTopicModel.py
bnpy/callbacks/HeldoutMetricsLogger.py
bnpy/callbacks/InferHeldoutTopics.py
bnpy/callbacks/__init__.py
bnpy/config/__init__.py
