Metadata-Version: 2.1
Name: bnpy
Version: 0.1.7
Summary: Bayesian nonparametric machine learning for Python
Home-page: https://github.com/bnpy/bnpy
Author: Michael C. Hughes
Author-email: mike@michaelchughes.com
License: BSD
Project-URL: Documentation, https://bnpy.readthedocs.io
Project-URL: Source, https://github.com/bnpy/bnpy
Project-URL: Issue Tracker, https://github.com/bnpy/bnpy/issues
Keywords: Dirichlet process,mixture model,topic model,hidden Markov model
Platform: UNKNOWN
Classifier: Development Status :: 3 - Alpha
Classifier: License :: OSI Approved :: BSD License
License-File: LICENSE.txt
